plasmidfinder-3.0.1.dist-info/METADATA
plasmidfinder-3.0.1.dist-info/WHEEL
plasmidfinder-3.0.1.dist-info/entry_points.txt
plasmidfinder-3.0.1.dist-info/licenses/LICENSE
plasmidfinder/__init__.py
plasmidfinder/__main__.py
plasmidfinder/cge/__init__.py
plasmidfinder/cge/config.py
plasmidfinder/environment_variables.md
plasmidfinder/functions.py
plasmidfinder-3.0.1.dist-info/RECORD
