Metadata-Version: 2.1
Name: PlasmidFinder
Version: 3.0.1
Summary: The service identifies plasmids in total or partial sequenced isolates of bacteria.
Author-Email: Center for Genomic Epidemiology <food-cgehelp@dtu.dk>
License: Apache 2.0
Requires-Python: >=3.10
Requires-Dist: cgecore>=1.5.5
Requires-Dist: tabulate>=0.7.7
Requires-Dist: pandas
Requires-Dist: biopython
